alphaxiv_cli/__init__.py
alphaxiv_cli/alphaxiv-executable
alphaxiv_cli/runner.py
alphaxiv-0.0.7.dist-info/METADATA
alphaxiv-0.0.7.dist-info/WHEEL
alphaxiv-0.0.7.dist-info/entry_points.txt
alphaxiv-0.0.7.dist-info/top_level.txt
alphaxiv-0.0.7.dist-info/RECORD
