Metadata-Version: 2.4
Name: alphaxiv
Version: 0.0.7
Summary: CLI for AlphaXiv experiments
Author: AlphaXiv
Classifier: Programming Language :: Python :: 3
Classifier: Operating System :: OS Independent
Requires-Python: >=3.6
Dynamic: author
Dynamic: classifier
Dynamic: description
Dynamic: description-content-type
Dynamic: requires-python
Dynamic: summary
